<?xml version="1.0"?>
<!DOCTYPE hibernate-mapping PUBLIC "-//Hibernate/Hibernate Mapping DTD 3.0//EN" "http://www.hibernate.org/dtd/hibernate-mapping-3.0.dtd">

<hibernate-mapping auto-import="false" default-lazy="false">
	<import class="cz.csob.ency.workflow.model.EncyWorkflow" />
	<import class="cz.csob.ency.workflow.model.EncyWorkflowInstance" />
	<import class="cz.csob.ency.workflow.model.EncyWorkflowLink" />
	<import class="cz.csob.ency.workflow.model.EncyWorkflowState" />
	<import class="cz.csob.ency.workflow.model.EncyWorkflowStateInstance" />
	<import class="cz.csob.ency.workflow.model.EncyWorkflowTransition" />
	<import class="cz.csob.ency.workflow.model.EncyWorkflowTransitionInstance" />
	<class name="cz.csob.ency.workflow.model.impl.EncyWorkflowImpl" table="ency_workflow">
		<id access="com.liferay.portal.dao.orm.hibernate.LiferayPropertyAccessor" name="workflowId" type="long">
			<generator class="assigned" />
		</id>
		<property access="com.liferay.portal.dao.orm.hibernate.LiferayPropertyAccessor" column="uuid_" name="uuid" type="com.liferay.portal.dao.orm.hibernate.StringType" />
		<property access="com.liferay.portal.dao.orm.hibernate.LiferayPropertyAccessor" name="className" type="com.liferay.portal.dao.orm.hibernate.StringType" />
		<property access="com.liferay.portal.dao.orm.hibernate.LiferayPropertyAccessor" name="title" type="com.liferay.portal.dao.orm.hibernate.StringType" />
		<property access="com.liferay.portal.dao.orm.hibernate.LiferayPropertyAccessor" name="description" type="com.liferay.portal.dao.orm.hibernate.StringClobType" />
		<property access="com.liferay.portal.dao.orm.hibernate.LiferayPropertyAccessor" name="initialStateName" type="com.liferay.portal.dao.orm.hibernate.StringType" />
		<property access="com.liferay.portal.dao.orm.hibernate.LiferayPropertyAccessor" name="version" type="com.liferay.portal.dao.orm.hibernate.LongType" />
		<property access="com.liferay.portal.dao.orm.hibernate.LiferayPropertyAccessor" column="active_" name="active" type="com.liferay.portal.dao.orm.hibernate.BooleanType" />
		<property access="com.liferay.portal.dao.orm.hibernate.LiferayPropertyAccessor" name="createDate" type="org.hibernate.type.TimestampType" />
		<property access="com.liferay.portal.dao.orm.hibernate.LiferayPropertyAccessor" name="modifiedDate" type="org.hibernate.type.TimestampType" />
	</class>
	<class name="cz.csob.ency.workflow.model.impl.EncyWorkflowInstanceImpl" table="ency_workflowinstance">
		<id access="com.liferay.portal.dao.orm.hibernate.LiferayPropertyAccessor" name="workflowInstanceId" type="long">
			<generator class="assigned" />
		</id>
		<property access="com.liferay.portal.dao.orm.hibernate.LiferayPropertyAccessor" column="uuid_" name="uuid" type="com.liferay.portal.dao.orm.hibernate.StringType" />
		<property access="com.liferay.portal.dao.orm.hibernate.LiferayPropertyAccessor" name="groupId" type="com.liferay.portal.dao.orm.hibernate.LongType" />
		<property access="com.liferay.portal.dao.orm.hibernate.LiferayPropertyAccessor" name="companyId" type="com.liferay.portal.dao.orm.hibernate.LongType" />
		<property access="com.liferay.portal.dao.orm.hibernate.LiferayPropertyAccessor" name="userId" type="com.liferay.portal.dao.orm.hibernate.LongType" />
		<property access="com.liferay.portal.dao.orm.hibernate.LiferayPropertyAccessor" name="userName" type="com.liferay.portal.dao.orm.hibernate.StringType" />
		<property access="com.liferay.portal.dao.orm.hibernate.LiferayPropertyAccessor" name="createDate" type="org.hibernate.type.TimestampType" />
		<property access="com.liferay.portal.dao.orm.hibernate.LiferayPropertyAccessor" name="modifiedDate" type="org.hibernate.type.TimestampType" />
		<property access="com.liferay.portal.dao.orm.hibernate.LiferayPropertyAccessor" name="workflowId" type="com.liferay.portal.dao.orm.hibernate.LongType" />
		<property access="com.liferay.portal.dao.orm.hibernate.LiferayPropertyAccessor" name="workflowVersion" type="com.liferay.portal.dao.orm.hibernate.LongType" />
		<property access="com.liferay.portal.dao.orm.hibernate.LiferayPropertyAccessor" name="className" type="com.liferay.portal.dao.orm.hibernate.StringType" />
		<property access="com.liferay.portal.dao.orm.hibernate.LiferayPropertyAccessor" name="classPK" type="com.liferay.portal.dao.orm.hibernate.LongType" />
		<property access="com.liferay.portal.dao.orm.hibernate.LiferayPropertyAccessor" name="workflowContext" type="com.liferay.portal.dao.orm.hibernate.StringClobType" />
	</class>
	<class name="cz.csob.ency.workflow.model.impl.EncyWorkflowLinkImpl" table="ency_workflowlink">
		<id access="com.liferay.portal.dao.orm.hibernate.LiferayPropertyAccessor" name="workflowLinkId" type="long">
			<generator class="assigned" />
		</id>
		<property access="com.liferay.portal.dao.orm.hibernate.LiferayPropertyAccessor" column="uuid_" name="uuid" type="com.liferay.portal.dao.orm.hibernate.StringType" />
		<property access="com.liferay.portal.dao.orm.hibernate.LiferayPropertyAccessor" name="groupId" type="com.liferay.portal.dao.orm.hibernate.LongType" />
		<property access="com.liferay.portal.dao.orm.hibernate.LiferayPropertyAccessor" name="companyId" type="com.liferay.portal.dao.orm.hibernate.LongType" />
		<property access="com.liferay.portal.dao.orm.hibernate.LiferayPropertyAccessor" name="userId" type="com.liferay.portal.dao.orm.hibernate.LongType" />
		<property access="com.liferay.portal.dao.orm.hibernate.LiferayPropertyAccessor" name="userName" type="com.liferay.portal.dao.orm.hibernate.StringType" />
		<property access="com.liferay.portal.dao.orm.hibernate.LiferayPropertyAccessor" name="createDate" type="org.hibernate.type.TimestampType" />
		<property access="com.liferay.portal.dao.orm.hibernate.LiferayPropertyAccessor" name="modifiedDate" type="org.hibernate.type.TimestampType" />
		<property access="com.liferay.portal.dao.orm.hibernate.LiferayPropertyAccessor" name="className" type="com.liferay.portal.dao.orm.hibernate.StringType" />
		<property access="com.liferay.portal.dao.orm.hibernate.LiferayPropertyAccessor" name="folderClassName" type="com.liferay.portal.dao.orm.hibernate.StringType" />
		<property access="com.liferay.portal.dao.orm.hibernate.LiferayPropertyAccessor" name="folderPK" type="com.liferay.portal.dao.orm.hibernate.LongType" />
		<property access="com.liferay.portal.dao.orm.hibernate.LiferayPropertyAccessor" name="workflowId" type="com.liferay.portal.dao.orm.hibernate.LongType" />
	</class>
	<class name="cz.csob.ency.workflow.model.impl.EncyWorkflowStateImpl" table="ency_workflowstate">
		<id access="com.liferay.portal.dao.orm.hibernate.LiferayPropertyAccessor" name="stateId" type="long">
			<generator class="assigned" />
		</id>
		<property access="com.liferay.portal.dao.orm.hibernate.LiferayPropertyAccessor" column="uuid_" name="uuid" type="com.liferay.portal.dao.orm.hibernate.StringType" />
		<property access="com.liferay.portal.dao.orm.hibernate.LiferayPropertyAccessor" name="workflowId" type="com.liferay.portal.dao.orm.hibernate.LongType" />
		<property access="com.liferay.portal.dao.orm.hibernate.LiferayPropertyAccessor" name="name" type="com.liferay.portal.dao.orm.hibernate.StringType" />
		<property access="com.liferay.portal.dao.orm.hibernate.LiferayPropertyAccessor" name="title" type="com.liferay.portal.dao.orm.hibernate.StringType" />
		<property access="com.liferay.portal.dao.orm.hibernate.LiferayPropertyAccessor" name="description" type="com.liferay.portal.dao.orm.hibernate.StringClobType" />
		<property access="com.liferay.portal.dao.orm.hibernate.LiferayPropertyAccessor" name="version" type="com.liferay.portal.dao.orm.hibernate.LongType" />
		<property access="com.liferay.portal.dao.orm.hibernate.LiferayPropertyAccessor" name="isInitial" type="com.liferay.portal.dao.orm.hibernate.BooleanType" />
		<property access="com.liferay.portal.dao.orm.hibernate.LiferayPropertyAccessor" name="isFinal" type="com.liferay.portal.dao.orm.hibernate.BooleanType" />
		<property access="com.liferay.portal.dao.orm.hibernate.LiferayPropertyAccessor" name="isEditable" type="com.liferay.portal.dao.orm.hibernate.BooleanType" />
		<property access="com.liferay.portal.dao.orm.hibernate.LiferayPropertyAccessor" name="isSearchable" type="com.liferay.portal.dao.orm.hibernate.BooleanType" />
		<property access="com.liferay.portal.dao.orm.hibernate.LiferayPropertyAccessor" name="isPermanent" type="com.liferay.portal.dao.orm.hibernate.BooleanType" />
		<property access="com.liferay.portal.dao.orm.hibernate.LiferayPropertyAccessor" name="cssIcon" type="com.liferay.portal.dao.orm.hibernate.StringType" />
		<property access="com.liferay.portal.dao.orm.hibernate.LiferayPropertyAccessor" name="cssIconColor" type="com.liferay.portal.dao.orm.hibernate.StringType" />
		<property access="com.liferay.portal.dao.orm.hibernate.LiferayPropertyAccessor" name="cssLabelColor" type="com.liferay.portal.dao.orm.hibernate.StringType" />
		<property access="com.liferay.portal.dao.orm.hibernate.LiferayPropertyAccessor" column="active_" name="active" type="com.liferay.portal.dao.orm.hibernate.BooleanType" />
		<property access="com.liferay.portal.dao.orm.hibernate.LiferayPropertyAccessor" name="createDate" type="org.hibernate.type.TimestampType" />
		<property access="com.liferay.portal.dao.orm.hibernate.LiferayPropertyAccessor" name="modifiedDate" type="org.hibernate.type.TimestampType" />
	</class>
	<class name="cz.csob.ency.workflow.model.impl.EncyWorkflowStateInstanceImpl" table="ency_workflowstateinstance">
		<id access="com.liferay.portal.dao.orm.hibernate.LiferayPropertyAccessor" name="stateInstanceId" type="long">
			<generator class="assigned" />
		</id>
		<property access="com.liferay.portal.dao.orm.hibernate.LiferayPropertyAccessor" column="uuid_" name="uuid" type="com.liferay.portal.dao.orm.hibernate.StringType" />
		<property access="com.liferay.portal.dao.orm.hibernate.LiferayPropertyAccessor" name="stateId" type="com.liferay.portal.dao.orm.hibernate.LongType" />
		<property access="com.liferay.portal.dao.orm.hibernate.LiferayPropertyAccessor" name="workflowId" type="com.liferay.portal.dao.orm.hibernate.LongType" />
		<property access="com.liferay.portal.dao.orm.hibernate.LiferayPropertyAccessor" name="workflowInstanceId" type="com.liferay.portal.dao.orm.hibernate.LongType" />
		<property access="com.liferay.portal.dao.orm.hibernate.LiferayPropertyAccessor" name="version" type="com.liferay.portal.dao.orm.hibernate.LongType" />
		<property access="com.liferay.portal.dao.orm.hibernate.LiferayPropertyAccessor" name="groupId" type="com.liferay.portal.dao.orm.hibernate.LongType" />
		<property access="com.liferay.portal.dao.orm.hibernate.LiferayPropertyAccessor" name="companyId" type="com.liferay.portal.dao.orm.hibernate.LongType" />
		<property access="com.liferay.portal.dao.orm.hibernate.LiferayPropertyAccessor" name="userId" type="com.liferay.portal.dao.orm.hibernate.LongType" />
		<property access="com.liferay.portal.dao.orm.hibernate.LiferayPropertyAccessor" name="userName" type="com.liferay.portal.dao.orm.hibernate.StringType" />
		<property access="com.liferay.portal.dao.orm.hibernate.LiferayPropertyAccessor" name="createDate" type="org.hibernate.type.TimestampType" />
		<property access="com.liferay.portal.dao.orm.hibernate.LiferayPropertyAccessor" name="modifiedDate" type="org.hibernate.type.TimestampType" />
		<property access="com.liferay.portal.dao.orm.hibernate.LiferayPropertyAccessor" name="completedDate" type="org.hibernate.type.TimestampType" />
		<property access="com.liferay.portal.dao.orm.hibernate.LiferayPropertyAccessor" name="workflowContext" type="com.liferay.portal.dao.orm.hibernate.StringClobType" />
	</class>
	<class name="cz.csob.ency.workflow.model.impl.EncyWorkflowTransitionImpl" table="ency_workflowtransition">
		<id access="com.liferay.portal.dao.orm.hibernate.LiferayPropertyAccessor" name="transitionId" type="long">
			<generator class="assigned" />
		</id>
		<property access="com.liferay.portal.dao.orm.hibernate.LiferayPropertyAccessor" column="uuid_" name="uuid" type="com.liferay.portal.dao.orm.hibernate.StringType" />
		<property access="com.liferay.portal.dao.orm.hibernate.LiferayPropertyAccessor" name="stateId" type="com.liferay.portal.dao.orm.hibernate.LongType" />
		<property access="com.liferay.portal.dao.orm.hibernate.LiferayPropertyAccessor" name="workflowId" type="com.liferay.portal.dao.orm.hibernate.LongType" />
		<property access="com.liferay.portal.dao.orm.hibernate.LiferayPropertyAccessor" name="version" type="com.liferay.portal.dao.orm.hibernate.LongType" />
		<property access="com.liferay.portal.dao.orm.hibernate.LiferayPropertyAccessor" name="name" type="com.liferay.portal.dao.orm.hibernate.StringType" />
		<property access="com.liferay.portal.dao.orm.hibernate.LiferayPropertyAccessor" name="title" type="com.liferay.portal.dao.orm.hibernate.StringType" />
		<property access="com.liferay.portal.dao.orm.hibernate.LiferayPropertyAccessor" name="description" type="com.liferay.portal.dao.orm.hibernate.StringClobType" />
		<property access="com.liferay.portal.dao.orm.hibernate.LiferayPropertyAccessor" name="targetStateName" type="com.liferay.portal.dao.orm.hibernate.StringType" />
		<property access="com.liferay.portal.dao.orm.hibernate.LiferayPropertyAccessor" name="targetStateId" type="com.liferay.portal.dao.orm.hibernate.LongType" />
		<property access="com.liferay.portal.dao.orm.hibernate.LiferayPropertyAccessor" name="cssIcon" type="com.liferay.portal.dao.orm.hibernate.StringType" />
		<property access="com.liferay.portal.dao.orm.hibernate.LiferayPropertyAccessor" name="cssIconColor" type="com.liferay.portal.dao.orm.hibernate.StringType" />
		<property access="com.liferay.portal.dao.orm.hibernate.LiferayPropertyAccessor" column="active_" name="active" type="com.liferay.portal.dao.orm.hibernate.BooleanType" />
		<property access="com.liferay.portal.dao.orm.hibernate.LiferayPropertyAccessor" name="createDate" type="org.hibernate.type.TimestampType" />
		<property access="com.liferay.portal.dao.orm.hibernate.LiferayPropertyAccessor" name="modifiedDate" type="org.hibernate.type.TimestampType" />
		<property access="com.liferay.portal.dao.orm.hibernate.LiferayPropertyAccessor" column="order_" name="order" type="com.liferay.portal.dao.orm.hibernate.LongType" />
	</class>
	<class name="cz.csob.ency.workflow.model.impl.EncyWorkflowTransitionInstanceImpl" table="ency_workflowtransitioninstance">
		<id access="com.liferay.portal.dao.orm.hibernate.LiferayPropertyAccessor" name="transitionInstanceId" type="long">
			<generator class="assigned" />
		</id>
		<property access="com.liferay.portal.dao.orm.hibernate.LiferayPropertyAccessor" column="uuid_" name="uuid" type="com.liferay.portal.dao.orm.hibernate.StringType" />
		<property access="com.liferay.portal.dao.orm.hibernate.LiferayPropertyAccessor" name="transitionId" type="com.liferay.portal.dao.orm.hibernate.LongType" />
		<property access="com.liferay.portal.dao.orm.hibernate.LiferayPropertyAccessor" name="stateId" type="com.liferay.portal.dao.orm.hibernate.LongType" />
		<property access="com.liferay.portal.dao.orm.hibernate.LiferayPropertyAccessor" name="stateInstanceId" type="com.liferay.portal.dao.orm.hibernate.LongType" />
		<property access="com.liferay.portal.dao.orm.hibernate.LiferayPropertyAccessor" name="workflowId" type="com.liferay.portal.dao.orm.hibernate.LongType" />
		<property access="com.liferay.portal.dao.orm.hibernate.LiferayPropertyAccessor" name="workflowInstanceId" type="com.liferay.portal.dao.orm.hibernate.LongType" />
		<property access="com.liferay.portal.dao.orm.hibernate.LiferayPropertyAccessor" name="version" type="com.liferay.portal.dao.orm.hibernate.LongType" />
		<property access="com.liferay.portal.dao.orm.hibernate.LiferayPropertyAccessor" column="comment_" name="comment" type="com.liferay.portal.dao.orm.hibernate.StringType" />
		<property access="com.liferay.portal.dao.orm.hibernate.LiferayPropertyAccessor" name="targetStateId" type="com.liferay.portal.dao.orm.hibernate.LongType" />
		<property access="com.liferay.portal.dao.orm.hibernate.LiferayPropertyAccessor" name="targetStateInstanceId" type="com.liferay.portal.dao.orm.hibernate.LongType" />
		<property access="com.liferay.portal.dao.orm.hibernate.LiferayPropertyAccessor" name="groupId" type="com.liferay.portal.dao.orm.hibernate.LongType" />
		<property access="com.liferay.portal.dao.orm.hibernate.LiferayPropertyAccessor" name="companyId" type="com.liferay.portal.dao.orm.hibernate.LongType" />
		<property access="com.liferay.portal.dao.orm.hibernate.LiferayPropertyAccessor" name="userId" type="com.liferay.portal.dao.orm.hibernate.LongType" />
		<property access="com.liferay.portal.dao.orm.hibernate.LiferayPropertyAccessor" name="userName" type="com.liferay.portal.dao.orm.hibernate.StringType" />
		<property access="com.liferay.portal.dao.orm.hibernate.LiferayPropertyAccessor" name="createDate" type="org.hibernate.type.TimestampType" />
		<property access="com.liferay.portal.dao.orm.hibernate.LiferayPropertyAccessor" name="workflowContext" type="com.liferay.portal.dao.orm.hibernate.StringClobType" />
	</class>
</hibernate-mapping>